Products.statusmessages-5.0.7-py3.13-nspkg.pth
Products/statusmessages/__init__.py
Products/statusmessages/adapter.py
Products/statusmessages/configure.zcml
Products/statusmessages/interfaces.py
Products/statusmessages/message.py
Products/statusmessages/tests/__init__.py
Products/statusmessages/tests/test_adapter.py
Products/statusmessages/tests/test_doctests.py
Products/statusmessages/tests/test_encoding.py
products_statusmessages-5.0.7.dist-info/METADATA
products_statusmessages-5.0.7.dist-info/WHEEL
products_statusmessages-5.0.7.dist-info/namespace_packages.txt
products_statusmessages-5.0.7.dist-info/top_level.txt
products_statusmessages-5.0.7.dist-info/RECORD
