Metadata-Version: 2.4
Name: Products.statusmessages
Version: 5.0.7
Summary: statusmessages provides an easy way of handling internationalized status messages managed via an BrowserRequest adapter storing status messages in client-side cookies.
Home-page: https://pypi.org/project/Products.statusmessages
Author: Hanno Schlichting
Author-email: plone-developers@lists.sourceforge.net
License: BSD
Keywords: Zope CMF Plone status messages i18n
Classifier: Development Status :: 5 - Production/Stable
Classifier: Environment :: Web Environment
Classifier: Framework :: Plone
Classifier: Framework :: Plone :: 6.0
Classifier: Framework :: Plone :: Core
Classifier: Framework :: Zope :: 5
Classifier: License :: OSI Approved :: BSD License
Classifier: Programming Language :: Python
Classifier: Programming Language :: Python :: 3.8
Classifier: Programming Language :: Python :: 3.9
Classifier: Programming Language :: Python :: 3.10
Classifier: Programming Language :: Python :: 3.11
Requires-Python: >=3.8
Requires-Dist: setuptools
Requires-Dist: Zope
Provides-Extra: test
Dynamic: author
Dynamic: author-email
Dynamic: classifier
Dynamic: description
Dynamic: description-content-type
Dynamic: home-page
Dynamic: keywords
Dynamic: license
Dynamic: provides-extra
Dynamic: requires-dist
Dynamic: requires-python
Dynamic: summary
